pixiu/__init__.py
pixiu/__main__.py
pixiu/main.py
pixiu/pxtester.py
pixiu/api/__init__.py
pixiu/api/defines.py
pixiu/api/errors.py
pixiu/api/utils.py
pixiu/api/v1/__init__.py
pixiu/api/v1/account.py
pixiu/api/v1/api.py
pixiu/api/v1/order.py
pixiu/api/v1/symbol.py
pixiu/base/__init__.py
pixiu/base/api_base.py
pixiu/base/ea_base.py
pixiu/base/ea_node_transformer.py
pixiu/builder/__init__.py
pixiu/builder/ea_builder.py
pixiu/builder/tpeac_parser.py
pixiu/builder/helper/__init__.py
pixiu/builder/helper/code_writer.py
pixiu/builder/strategies/conf/module_indicators.json
pixiu/builder/strategies/conf/strategy_default.json
pixiu/live/__init__.py
pixiu/optimizer/__init__.py
pixiu/optimizer/ea_optimizer.py
pixiu/tester/__init__.py
pixiu/tester/ea_tester.py
pixiu/tester/ea_tester_context.py
pixiu/tester/ea_tester_graph.py
pixiu/tester/tester_api_v1.py
pixiu-0.170.0.dist-info/licenses/LICENSE
pixiu-0.170.0.dist-info/METADATA
pixiu-0.170.0.dist-info/WHEEL
pixiu-0.170.0.dist-info/entry_points.txt
pixiu-0.170.0.dist-info/top_level.txt
pixiu-0.170.0.dist-info/RECORD
