Metadata-Version: 2.4
Name: pixiu
Version: 0.170.0
Summary: PiXiu - A trading backtesting tool similar to MT4/MT5
Home-page: https://github.com/tradepython/pixiu
Author: tradepython
Author-email: tradepython@icloud.com
Project-URL: Bug Tracker, https://github.com/tradepython/pixiu/issues
Keywords: Trading Backtest Forex Stocks MT4 MT5 MetaTrade
Classifier: Programming Language :: Python :: 3
Classifier: License :: OSI Approved :: Apache Software License
Requires-Python: >=3.8
License-File: LICENSE
Requires-Dist: python-dateutil
Requires-Dist: RestrictedPython
Requires-Dist: numpy
Requires-Dist: pandas
Requires-Dist: TA-Lib
Requires-Dist: pymongo
Requires-Dist: tabulate
Requires-Dist: hashids
Requires-Dist: pytz
Requires-Dist: dash
Requires-Dist: plotly
Requires-Dist: pyjson5
Requires-Dist: jinja2
Requires-Dist: black
Provides-Extra: testing
Requires-Dist: WebTest>=1.3.1; extra == "testing"
Requires-Dist: pytest; extra == "testing"
Requires-Dist: pytest-cov; extra == "testing"
Dynamic: author
Dynamic: author-email
Dynamic: classifier
Dynamic: description
Dynamic: description-content-type
Dynamic: home-page
Dynamic: keywords
Dynamic: license-file
Dynamic: project-url
Dynamic: provides-extra
Dynamic: requires-dist
Dynamic: requires-python
Dynamic: summary
